lsd_lite/__init__.py
lsd_lite/affs.py
lsd_lite/lsds.py
lsd_lite-1.0.0.dist-info/licenses/LICENSE
lsd_lite-1.0.0.dist-info/METADATA
lsd_lite-1.0.0.dist-info/WHEEL
lsd_lite-1.0.0.dist-info/top_level.txt
lsd_lite-1.0.0.dist-info/RECORD
