Metadata-Version: 2.4
Name: lsd-lite
Version: 1.0.0
Summary: Simple LSD and affinity graph computation
Author-email: Arlo Sheridan <arlo@e11.bio>, Jan Funke <funkej@janelia.hhmi.org>, William Patton <wllmpttn24@gmail.com>
License: MIT
Classifier: Programming Language :: Python :: 3
Requires-Python: >=3.11
License-File: LICENSE
Requires-Dist: funlib.geometry>=0.3
Requires-Dist: scipy>=1.15.3
Provides-Extra: dev
Requires-Dist: pytest>=8.0; extra == "dev"
Requires-Dist: pytest-cov>=5.0; extra == "dev"
Requires-Dist: ruff>=0.6; extra == "dev"
Requires-Dist: ty>=0.0.1a21; extra == "dev"
Dynamic: license-file
